scdiffeq/__init__.py
scdiffeq/__version__.py
scdiffeq/_backend_utilities/__init__.py
scdiffeq/_backend_utilities/_configure_logging.py
scdiffeq/callbacks/__init__.py
scdiffeq/callbacks/_stochastic_weight_averaging.py
scdiffeq/core/__init__.py
scdiffeq/core/_scdiffeq.py
scdiffeq/core/_mix_ins/__init__.py
scdiffeq/core/_mix_ins/_knn_mix_in.py
scdiffeq/core/_mix_ins/_logging_mix_in.py
scdiffeq/core/_mix_ins/_model_config_mix_in.py
scdiffeq/core/_mix_ins/_state_characterization_mix_in.py
scdiffeq/core/_mix_ins/_training_routine_mix_ins.py
scdiffeq/core/_mix_ins/_utility_io_mix_in.py
scdiffeq/core/callbacks/__init__.py
scdiffeq/core/callbacks/_basic_progress_bar.py
scdiffeq/core/callbacks/_gradient_potential_callback.py
scdiffeq/core/callbacks/_intermittent_saves.py
scdiffeq/core/callbacks/_memory_monitor.py
scdiffeq/core/callbacks/_model_logging.py
scdiffeq/core/callbacks/_testing.py
scdiffeq/core/configs/__init__.py
scdiffeq/core/configs/_configure_time_key.py
scdiffeq/core/configs/_data_configuration.py
scdiffeq/core/configs/_lightning_callbacks_configuration.py
scdiffeq/core/configs/_lightning_model_configuration.py
scdiffeq/core/configs/_lightning_trainer_configuration.py
scdiffeq/core/configs/_progress_bar_config.py
scdiffeq/core/lightning_models/README.md
scdiffeq/core/lightning_models/__init__.py
scdiffeq/core/lightning_models/_lightning_ode.py
scdiffeq/core/lightning_models/_lightning_ode_fixed_potential.py
scdiffeq/core/lightning_models/_lightning_ode_prior_potential.py
scdiffeq/core/lightning_models/_lightning_ode_vae.py
scdiffeq/core/lightning_models/_lightning_ode_vae_fixed_potential.py
scdiffeq/core/lightning_models/_lightning_ode_vae_prior_potential.py
scdiffeq/core/lightning_models/_lightning_sde.py
scdiffeq/core/lightning_models/_lightning_sde_fate_bias_aware.py
scdiffeq/core/lightning_models/_lightning_sde_fixed_potential.py
scdiffeq/core/lightning_models/_lightning_sde_fixed_potential_regularized_velocity_ratio.py
scdiffeq-1.1.0.dist-info/METADATA
scdiffeq-1.1.0.dist-info/WHEEL
scdiffeq-1.1.0.dist-info/licenses/LICENSE
scdiffeq-1.1.0.dist-info/RECORD
