Metadata-Version: 2.4
Name: scdiffeq
Version: 1.1.0
Summary: scDiffEq: modeling single-cell dynamics using neural differential equations.
Project-URL: Homepage, https://github.com/scDiffEq/scDiffEq
Author-email: "Michael E. Vinyard" <mvinyard.ai@gmail.com>
License: MIT
License-File: LICENSE
Classifier: Development Status :: 2 - Pre-Alpha
Classifier: Intended Audience :: Science/Research
Classifier: Programming Language :: Python :: 3.11
Classifier: Topic :: Scientific/Engineering :: Bio-Informatics
Requires-Python: >=3.11
Requires-Dist: abcparse>=0.1.4
Requires-Dist: adata-query>=0.1.0
Requires-Dist: anndata>=0.11.3
Requires-Dist: autodevice>=0.0.2
Requires-Dist: cell-neighbors>=0.1.0
Requires-Dist: cell-perturb>=0.0.1rc1
Requires-Dist: cellplots>=0.0.1rc0
Requires-Dist: geomloss>=0.2.6
Requires-Dist: lightning>=2.1
Requires-Dist: neural-diffeqs>=0.3.2
Requires-Dist: pykeops>=2.1.2
Requires-Dist: requests
Requires-Dist: scanpy>=1.11.0
Requires-Dist: torch-adata>=0.1.1
Requires-Dist: torch-nets>=0.1.0
Requires-Dist: torch>=2.5.0
Requires-Dist: torchsde>=0.2.6
Requires-Dist: tqdm
Provides-Extra: dev
Requires-Dist: jupyter; extra == 'dev'
Requires-Dist: jupyterlab; extra == 'dev'
Provides-Extra: docs
Requires-Dist: autodoc; extra == 'docs'
Requires-Dist: ipython; extra == 'docs'
Requires-Dist: myst-parser; extra == 'docs'
Requires-Dist: nbsphinx; extra == 'docs'
Requires-Dist: numpy<2.0; extra == 'docs'
Requires-Dist: pydata-sphinx-theme; extra == 'docs'
Requires-Dist: scikit-learn>=1.5; extra == 'docs'
Requires-Dist: sphinx; extra == 'docs'
Requires-Dist: sphinx-autodoc-typehints; extra == 'docs'
Requires-Dist: sphinx-copybutton; extra == 'docs'
Requires-Dist: sphinx-design; extra == 'docs'
Requires-Dist: sphinx-favicon; extra == 'docs'
Requires-Dist: sphinxcontrib-napoleon; extra == 'docs'
